rtl/vce2_agu.sv
module vce2_agu #(
    parameter AddrWidth = 32
) (
    input logic clk_i,
    input logic rst_ni,

    // from/to PIPELINE
    input logic [AddrWidth-3:0] addr_i,
    output logic raddr_a_sel_o,                 // select signal for address of first port of RF, used to read rd
    output logic agu_addr_sel_o,                // select signal for multiplexer on agu's input, selects between rdata a and b

    // from/to VRF
    input logic load,           // parallel load for the counters
    input logic get_rs1,        // generate rs1
    input logic get_rs2,        // generate rs2
    input logic get_rd_noincr,  // generate rd without increment after
    input logic get_rd,         // generate rd
    output logic ready_o,       // load of addresses complete

    // to MEMORY interface
    output logic [AddrWidth-1:0] addr_o
);

    // counter signals
    logic incr_rs1, incr_rs2, incr_rd, ld_rs1, ld_rs2, ld_rd;
    logic [AddrWidth-3:0] addr_rs1_q, addr_rs2_q, addr_rd_q, addr_rs1_d, addr_rs2_d, addr_rd_d;
    // FSM signals
    logic [1:0] state, next_state;

    /////////
    // FSM //
    /////////

    always_ff @(posedge clk_i or negedge rst_ni) begin
        if (!rst_ni) begin
            state <= 2'b00;
        end else begin
            state <= next_state;
        end
    end

    always_comb begin
        ld_rs1 = 1'b0;
        ld_rs2 = 1'b0;
        ld_rd = 1'b0;
        raddr_a_sel_o = 1'b0;
        agu_addr_sel_o = 1'b0;
        ready_o = 1'b0;
        case (state)
            2'b00: begin
                if (load==1'b1) begin
                    next_state = 2'b01;
                    ld_rs1 = 1'b1;
                end else begin
                    next_state = 2'b00;
                end
            end
            2'b01: begin
                next_state = 2'b10;
                raddr_a_sel_o = 1'b1;   // select rd as first RF address
                ld_rd = 1'b1;
            end
            2'b10: begin
                next_state = 2'b11;
                agu_addr_sel_o = 1'b1;  // select the second RF port
                ld_rs2 = 1'b1;
            end
            2'b11: begin
                next_state = 2'b00;
                ready_o = 1;
            end
            default: next_state = 2'b00;
        endcase
    end

    //////////////
    // COUNTERS //
    //////////////

    // Sequential logic for the counters
    always_ff @(posedge clk_i or negedge rst_ni) begin
        if (!rst_ni) begin
            addr_rs1_q <= '0;
            addr_rs2_q <= '0;
            addr_rd_q <= '0;
        end else begin
            addr_rs1_q <= addr_rs1_d;
            addr_rs2_q <= addr_rs2_d;
            addr_rd_q <= addr_rd_d;
        end
    end

    // Combinational logic for the counters
    always_comb begin
        addr_rs1_d = ld_rs1 ? addr_i : incr_rs1 ? addr_rs1_q + 1 : addr_rs1_q;
        addr_rs2_d = ld_rs2 ? addr_i : incr_rs2 ? addr_rs2_q + 1 : addr_rs2_q;
        addr_rd_d = ld_rd ? addr_i : incr_rd ? addr_rd_q + 1 : addr_rd_q;
    end

    // Delayed increment for the read/write signals
    always_ff @(posedge clk_i or negedge rst_ni) begin
        if (!rst_ni) begin
            incr_rs1 <= 0;
            incr_rs2 <= 0;
            incr_rd <= 0;
        end else begin
            incr_rs1 <= get_rs1;
            incr_rs2 <= get_rs2;
            incr_rd <= get_rd;
        end
    end

    ////////////
    // OUTPUT //
    ////////////

    // Multiplexer for the output address
    always_comb begin
        addr_o = get_rs1 ? {addr_rs1_q, 2'b00} :
                 get_rs2 ? {addr_rs2_q, 2'b00} :
                 get_rd || get_rd_noincr ? {addr_rd_q, 2'b00} : '0;
    end

    
endmodule

tb/agu/wave.vcd
$version Generated by VerilatedVcd $end
$date Wed Apr 17 09:20:02 2024 $end
$timescale 1ps $end

 $scope module TOP $end
  $var wire 30 0 addr_i [29:0] $end
  $var wire 32 9 addr_o [31:0] $end
  $var wire  1 2 agu_addr_sel_o $end
  $var wire  1 . clk_i $end
  $var wire  1 7 get_rd $end
  $var wire  1 6 get_rd_noincr $end
  $var wire  1 4 get_rs1 $end
  $var wire  1 5 get_rs2 $end
  $var wire  1 3 load $end
  $var wire  1 1 raddr_a_sel_o $end
  $var wire  1 8 ready_o $end
  $var wire  1 / rst_ni $end
  $scope module vce2_agu $end
   $var wire 32 = AddrWidth [31:0] $end
   $var wire 30 0 addr_i [29:0] $end
   $var wire 32 9 addr_o [31:0] $end
   $var wire 30 < addr_rd_d [29:0] $end
   $var wire 30 ( addr_rd_q [29:0] $end
   $var wire 30 : addr_rs1_d [29:0] $end
   $var wire 30 & addr_rs1_q [29:0] $end
   $var wire 30 ; addr_rs2_d [29:0] $end
   $var wire 30 ' addr_rs2_q [29:0] $end
   $var wire  1 2 agu_addr_sel_o $end
   $var wire  1 . clk_i $end
   $var wire  1 7 get_rd $end
   $var wire  1 6 get_rd_noincr $end
   $var wire  1 4 get_rs1 $end
   $var wire  1 5 get_rs2 $end
   $var wire  1 % incr_rd $end
   $var wire  1 # incr_rs1 $end
   $var wire  1 $ incr_rs2 $end
   $var wire  1 , ld_rd $end
   $var wire  1 * ld_rs1 $end
   $var wire  1 + ld_rs2 $end
   $var wire  1 3 load $end
   $var wire  2 - next_state [1:0] $end
   $var wire  1 1 raddr_a_sel_o $end
   $var wire  1 8 ready_o $end
   $var wire  1 / rst_ni $end
   $var wire  2 ) state [1:0] $end
  $upscope $end
 $upscope $end
$enddefinitions $end


#0
0#
0$
0%
b000000000000000000000000000000 &
b000000000000000000000000000000 '
b000000000000000000000000000000 (
b00 )
1*
0+
0,
b01 -
1.
1/
b000000000000000000000000001010 0
01
02
13
04
05
06
07
08
b00000000000000000000000000000000 9
b000000000000000000000000001010 :
b000000000000000000000000000000 ;
b000000000000000000000000000000 <
b00000000000000000000000000100000 =
#1
0.
#2
b000000000000000000000000001010 &
b01 )
0*
1,
b10 -
1.
b000000000000000000000000010100 0
11
b000000000000000000000000010100 <
#3
0.
#4
b000000000000000000000000010100 (
b10 )
1+
0,
b11 -
1.
b000000000000000000000000101000 0
01
12
b000000000000000000000000101000 ;
#5
0.
#6
1#
b000000000000000000000000101000 '
b11 )
0+
b00 -
1.
02
03
14
18
b00000000000000000000000000101000 9
b000000000000000000000000001011 :
#7
0.
#8
0#
1$
b000000000000000000000000001011 &
b00 )
1.
04
15
08
b00000000000000000000000010100000 9
b000000000000000000000000101001 ;
#9
0.
#10
0$
b000000000000000000000000101001 '
1.
05
16
b00000000000000000000000001010000 9
#11
0.
#12
1%
1.
06
17
b000000000000000000000000010101 <
#13
0.
#14
0%
b000000000000000000000000010101 (
1.
07
b00000000000000000000000000000000 9
