rtl/vce2_agu.sv
module vce2_agu #(
    parameter AddrWidth = 32
) (
    input logic clk_i,
    input logic rst_ni,

    // from PIPELINE
    input logic [AddrWidth-3:0] addr_rs1_i,
    input logic [AddrWidth-3:0] addr_rs2_i,
    input logic [AddrWidth-3:0] addr_rd_i,

    // from VRF
    input logic load,           // parallel load for the counters
    input logic get_rs1,        // generate rs1
    input logic get_rs2,        // generate rs2
    input logic get_rd_noincr,  // generate rd without increment after
    input logic get_rd,         // generate rd

    // to MEMORY interface
    output logic [AddrWidth-1:0] addr_o
);

    logic incr_rs1, incr_rs2, incr_rd;
    logic [AddrWidth-3:0] addr_rs1_s, addr_rs2_s, addr_rd_s;

    // Four 30 bit counters for the addresses
    always_ff @(posedge clk_i or negedge rst_ni) begin
        if (!rst_ni) begin
            addr_rs1_s <= 0;
            addr_rs2_s <= 0;
            addr_rd_s <= 0;
        end else begin
            if (load) begin
                addr_rs1_s <= addr_rs1_i;
                addr_rs2_s <= addr_rs2_i;
                addr_rd_s <= addr_rd_i;
            end else begin
                addr_rs1_s <= incr_rs1 ? addr_rs1_s + 1 : addr_rs1_s;
                addr_rs2_s <= incr_rs2 ? addr_rs2_s + 1 : addr_rs2_s;
                addr_rd_s <= incr_rd ? addr_rd_s + 1 : addr_rd_s;
            end
        end
    end

    // Delayed increment for the read/write signals
    always_ff @(posedge clk_i or negedge rst_ni) begin
        if (!rst_ni) begin
            incr_rs1 <= 0;
            incr_rs2 <= 0;
            incr_rd <= 0;
        end else begin
            incr_rs1 <= get_rs1;
            incr_rs2 <= get_rs2;
            incr_rd <= get_rd;
        end
    end

    // Multiplexer for the output address
    always_comb begin
        addr_o = get_rs1 ? {addr_rs1_s, 2'b00} :
                 get_rs2 ? {addr_rs2_s, 2'b00} :
                 get_rd || get_rd_noincr ? {addr_rd_s, 2'b00} : '0;
    end

    
endmodule

tb/agu/wave.vcd
$version Generated by VerilatedVcd $end
$date Tue Apr 16 13:11:16 2024 $end
$timescale 1ps $end

 $scope module TOP $end
  $var wire 32 3 addr_o [31:0] $end
  $var wire 30 - addr_rd_i [29:0] $end
  $var wire 30 + addr_rs1_i [29:0] $end
  $var wire 30 , addr_rs2_i [29:0] $end
  $var wire  1 ) clk_i $end
  $var wire  1 2 get_rd $end
  $var wire  1 1 get_rd_noincr $end
  $var wire  1 / get_rs1 $end
  $var wire  1 0 get_rs2 $end
  $var wire  1 . load $end
  $var wire  1 * rst_ni $end
  $scope module vce2_agu $end
   $var wire 32 4 AddrWidth [31:0] $end
   $var wire 32 3 addr_o [31:0] $end
   $var wire 30 - addr_rd_i [29:0] $end
   $var wire 30 ( addr_rd_s [29:0] $end
   $var wire 30 + addr_rs1_i [29:0] $end
   $var wire 30 & addr_rs1_s [29:0] $end
   $var wire 30 , addr_rs2_i [29:0] $end
   $var wire 30 ' addr_rs2_s [29:0] $end
   $var wire  1 ) clk_i $end
   $var wire  1 2 get_rd $end
   $var wire  1 1 get_rd_noincr $end
   $var wire  1 / get_rs1 $end
   $var wire  1 0 get_rs2 $end
   $var wire  1 % incr_rd $end
   $var wire  1 # incr_rs1 $end
   $var wire  1 $ incr_rs2 $end
   $var wire  1 . load $end
   $var wire  1 * rst_ni $end
  $upscope $end
 $upscope $end
$enddefinitions $end


#0
0#
0$
0%
b000000000000000000000000000000 &
b000000000000000000000000000000 '
b000000000000000000000000000000 (
1)
0*
b000000000000000000000000000000 +
b000000000000000000000000000000 ,
b000000000000000000000000000000 -
0.
0/
00
01
02
b00000000000000000000000000000000 3
b00000000000000000000000000100000 4
#1
0)
#2
1)
1*
#3
0)
#4
b000000000000000000000000001010 &
b000000000000000000000000010100 '
b000000000000000000000000011110 (
1)
b000000000000000000000000001010 +
b000000000000000000000000010100 ,
b000000000000000000000000011110 -
1.
#5
0)
#6
1#
1)
b000000000000000000000000000000 +
b000000000000000000000000000000 ,
b000000000000000000000000000000 -
0.
1/
b00000000000000000000000000101000 3
#7
0)
#8
0#
1$
b000000000000000000000000001011 &
1)
0/
10
b00000000000000000000000001010000 3
#9
0)
#10
0$
b000000000000000000000000010101 '
1)
00
11
b00000000000000000000000001111000 3
#11
0)
#12
1%
1)
01
12
#13
0)
#14
0%
b000000000000000000000000011111 (
1)
02
b00000000000000000000000000000000 3
